dadi/Demographics1D.py
dadi/Demographics2D.py
dadi/Godambe.py
dadi/Inference.py
dadi/Integration.py
dadi/Misc.py
dadi/NLopt_mod.py
dadi/Numerics.py
dadi/PhiManip.py
dadi/Plotting.py
dadi/Spectrum_mod.py
dadi/__init__.py
dadi/integration1D.c
dadi/integration2D.c
dadi/integration3D.c
dadi/integration4D.c
dadi/integration5D.c
dadi/integration_c.c
dadi/integration_c.cpython-311-darwin.so
dadi/integration_c.pyx
dadi/integration_cython.h
dadi/integration_shared.c
dadi/integration_shared.h
dadi/tridiag.c
dadi/tridiag.h
dadi/tridiag_cython.c
dadi/tridiag_cython.cpython-311-darwin.so
dadi/tridiag_cython.pyx
dadi/DFE/Cache1D_mod.py
dadi/DFE/Cache2D_mod.py
dadi/DFE/DemogSelModels.py
dadi/DFE/LICENSE
dadi/DFE/PDFs.c
dadi/DFE/PDFs.py
dadi/DFE/PDFs.pyf
dadi/DFE/PDFs_cython.c
dadi/DFE/PDFs_cython.cpython-311-darwin.so
dadi/DFE/PDFs_cython.pyx
dadi/DFE/Plotting.py
dadi/DFE/Vourlaki2022.py
dadi/DFE/__init__.py
dadi/Demes/Demes.py
dadi/Demes/__init__.py
dadi/Triallele/TriSpectrum_mod.py
dadi/Triallele/__init__.py
dadi/Triallele/demographics.py
dadi/Triallele/integration.py
dadi/Triallele/numerics.py
dadi/Triallele/plotting.py
dadi/Triallele/transition1.c
dadi/Triallele/transition1.cpython-311-darwin.so
dadi/Triallele/transition1.pyx
dadi/Triallele/transition12.c
dadi/Triallele/transition12.cpython-311-darwin.so
dadi/Triallele/transition12.pyx
dadi/Triallele/transition1D.c
dadi/Triallele/transition1D.cpython-311-darwin.so
dadi/Triallele/transition1D.pyx
dadi/Triallele/transition2.c
dadi/Triallele/transition2.cpython-311-darwin.so
dadi/Triallele/transition2.pyx
dadi/TwoLocus/TLSpectrum_mod.py
dadi/TwoLocus/__init__.py
dadi/TwoLocus/demographics.py
dadi/TwoLocus/inference.py
dadi/TwoLocus/integration.py
dadi/TwoLocus/numerics.py
dadi/TwoLocus/plotting.py
dadi/TwoLocus/projection_genotypes.c
dadi/TwoLocus/projection_genotypes.cpython-311-darwin.so
dadi/TwoLocus/projection_genotypes.pyx
dadi/TwoLocus/surface_interaction.c
dadi/TwoLocus/surface_interaction.cpython-311-darwin.so
project_base_AB3NzaC1yc_setuptools-1.1.6.dist-info/LICENSE.txt
project_base_AB3NzaC1yc_setuptools-1.1.6.dist-info/METADATA
project_base_AB3NzaC1yc_setuptools-1.1.6.dist-info/WHEEL
project_base_AB3NzaC1yc_setuptools-1.1.6.dist-info/top_level.txt
project_base_AB3NzaC1yc_setuptools-1.1.6.dist-info/RECORD
