Metadata-Version: 2.1
Name: project-base-AB3NzaC1yc-setuptools
Version: 1.1.6
Summary: Fit population genetic models of demography and selection using diffusion approximations to the allele frequency spectrum
Author-email: Ryan Gutenkunst <rgutenk@arizona.edu>
Project-URL: Documentation, https://dadi.readthedocs.io/en/latest/
Project-URL: Source, https://bitbucket.org/gutenkunstlab/dadi
Classifier: Development Status :: 5 - Production/Stable
Classifier: Intended Audience :: Science/Research
Classifier: License :: OSI Approved :: BSD License
Classifier: Natural Language :: English
Classifier: Operating System :: OS Independent
Classifier: Programming Language :: Python :: 3
Classifier: Topic :: Scientific/Engineering :: Bio-Informatics
Requires-Python: >=3.7
License-File: LICENSE.txt
Requires-Dist: matplotlib
Requires-Dist: numpy
Requires-Dist: scipy
Requires-Dist: nlopt (>=2.7.1)
